README.rst
setup.cfg
setup.py
django_gcs/__init__.py
django_gcs/settings.py
django_gcs/storage.py
django_gcs.egg-info/PKG-INFO
django_gcs.egg-info/SOURCES.txt
django_gcs.egg-info/dependency_links.txt
django_gcs.egg-info/requires.txt
django_gcs.egg-info/top_level.txt