Metadata-Version: 1.1
Name: django-gcs
Version: 0.1.1
Summary: Django file storage backend for Google Cloud Storage
Home-page: https://github.com/bodja/django-gcs
Author: Bogdan Radko
Author-email: bodja.rules@gmail.com
License: MIT
Download-URL: https://github.com/bodja/django-gcs/tarball/0.1.1
Keywords: django,storage,gcs,google cloud storage
Platform: UNKNOWN
